importmod/__init__.py
importmod/atom.py
importmod/config.py
importmod/deps.py
importmod/games.py
importmod/generate.py
importmod/main.py
importmod/update.py
importmod/util.py
importmod/validate.py
importmod/sources/__init__.py
importmod/sources/github.py
importmod/sources/gitlab.py
importmod/sources/modhistory.py
importmod/sources/nexus.py
importmod/sources/pypi.py
importmod_core/__init__.py
importmod_core/datadir.py
importmod_core/install.py
importmod_core/main.py
importmod_core/names.py
importmod_core/prompt.py
importmod_core/textures.py
importmod-0.7.3.dist-info/LICENSE
importmod-0.7.3.dist-info/METADATA
importmod-0.7.3.dist-info/WHEEL
importmod-0.7.3.dist-info/entry_points.txt
importmod-0.7.3.dist-info/top_level.txt
importmod-0.7.3.dist-info/RECORD
